drb/extractor/__init__.py
drb/extractor/_version.py
drb/extractor/extractor.py
drb_extractor-1.2.0.dist-info/LICENCE.txt
drb_extractor-1.2.0.dist-info/METADATA
drb_extractor-1.2.0.dist-info/WHEEL
drb_extractor-1.2.0.dist-info/top_level.txt
drb_extractor-1.2.0.dist-info/RECORD
